picharsso/__init__.py
picharsso/__main__.py
picharsso/meta.py
picharsso/utils.py
picharsso/cli/__init__.py
picharsso/cli/info.py
picharsso/cli/draw/__init__.py
picharsso/cli/draw/braille.py
picharsso/cli/draw/gradient.py
picharsso/data/logo.txt
picharsso/draw/__init__.py
picharsso/draw/base.py
picharsso/draw/braille.py
picharsso/draw/gradient.py
picharsso/format/__init__.py
picharsso/format/ansi.py
picharsso/format/base.py
picharsso/format/html.py
picharsso-2.0.1.dist-info/LICENSE
picharsso-2.0.1.dist-info/METADATA
picharsso-2.0.1.dist-info/WHEEL
picharsso-2.0.1.dist-info/entry_points.txt
picharsso-2.0.1.dist-info/top_level.txt
picharsso-2.0.1.dist-info/RECORD
