Metadata-Version: 2.1
Name: picharsso
Version: 2.0.1
Summary: A utility for converting images to text art.
Home-page: UNKNOWN
Author: Kelvin DeCosta
Author-email: decostakelvin@gmail.com
License: MIT
Project-URL: Documentation, https://kelvindecosta.github.io/picharsso
Project-URL: Source, https://github.com/kelvindecosta/picharsso
Platform: UNKNOWN
Classifier: Programming Language :: Python :: 3
Classifier: Operating System :: OS Independent
Classifier: License :: OSI Approved :: MIT License
Classifier: Development Status :: 5 - Production/Stable
Classifier: Topic :: Artistic Software
Classifier: Topic :: Terminals
Classifier: Topic :: Utilities
Requires-Python: >=3.8
Requires-Dist: click
Requires-Dist: numpy
Requires-Dist: pillow
Requires-Dist: sty
